Workbook

Sheet 使い方
B2: 資産運用シミュレーション（楽天証券の保有資産と連動）
B4: ■ 手順1：楽天証券から保有資産をCSVで保存
B5: ・楽天証券のWebサイト（PC版）にログインし、「口座管理」→「保有商品一覧」を開く
B6: ・画面上の「CSVで保存」から保有商品一覧のCSVファイルをダウンロード
B7: ※スマホアプリ（iSPEED）ではCSVを保存できないため、ブラウザのPC版サイトを使ってください
B9: ■ 手順2：「保有資産」シートに取り込む（どちらか一つ）
B10: A. CSVファイルをClaudeとのチャットにアップロードする → Claudeが取り込みを行います
B11: B. PCにPythonがある場合：python 楽天証券CSV取込.py 保有商品一覧.csv 資産運用シミュレーション.xlsx
B12: C. 手入力：CSVの各列の値を「保有資産」シートの黄色の列にコピー＆貼り付け
B14: ■ 手順3：「シミュレーション」シートの黄色いセルを入力
B15: ・毎月の積立額（楽天証券の「積立設定一覧」で確認できます）、想定利回り、運用期間など
B16: ・保有資産の時価評価額合計が自動で「初期資産」になります（手入力欄に入れるとそちらが優先）
... B26: ・実際の運用成果は市場の変動で大きく上下します。将来の結果を保証するものではありません

Sheet シミュレーション
A1: 資産運用シミュレーション
A3: 入力項目（黄色のセルを入力）
A4: 現在の年齢 | B4: 35 | C4: 歳
A5: 現在の保有資産（楽天証券） | B5: =保有資産!B4 -> 0 | C5: 円 | D5: 「保有資産」シートの時価評価額合計
A6: 初期資産の手入力（任意） | C6: 円 | D6: 入力するとこちらを優先（空欄なら上の値を使用）
A7: シミュレーションに使う初期資産 | B7: =IF(B6="",B5,B6) -> 0 | C7: 円
A8: 毎月の積立額 | B8: 30000 | C8: 円 | D8: 楽天証券の「積立設定一覧」の合計額
A9: 想定年利回り | B9: 0.05 | D9: 例：全世界株式 4〜7%／バランス型 2〜4%
A10: 運用期間 | B10: 20 | C10: 年 | D10: 1〜50年
A11: 積立額の年間増加率 | B11: 0 | D11: 毎年積立額を増やす場合（例：3%）
A12: 運用益にかかる税率 | B12: 0 | D12: NISAは0%、特定口座・一般口座は20.315%
A13: 想定インフレ率 | B13: 0.02 | D13: 将来の金額を今の価値に換算するために使用
A14: 月利（年利回りから換算） | B14: =(1+B9)^(1/12)-1 -> 0.0040741238 | D14: 計算用
A16: 結果
A17: 運用終了時の年齢 | B17: =B4+B10 -> 55 | C17: 歳
A18: 投資元本の合計 | B18: =INDEX(年次推移!E$5:E$55,$B$10+1) -> 7200000 | C18: 円
A19: 最終資産額 | B19: =INDEX(年次推移!F$5:F$55,$B$10+1) -> 12174135 | C19: 円
A20: 運用益 | B20: =INDEX(年次推移!G$5:G$55,$B$10+1) -> 4974134.6 | C20: 円
A21: 税引後の受取額 | B21: =INDEX(年次推移!H$5:H$55,$B$10+1) -> 12174135 | C21: 円
A22: 今の価値に換算（インフレ考慮） | B22: =INDEX(年次推移!I$5:I$55,$B$10+1) -> 8192843.6 | C22: 円
A23: 資産倍率（最終資産額÷元本） | B23: =IF(B18=0,0,B19/B18) -> 1.690852 | C23: 倍

Sheet 保有資産
A1: 楽天証券 保有資産（保有商品一覧CSVより）
A2: データ取得日
D3: 口座区分別（円） | G3: 商品種別（円）
A4: 時価評価額 合計（円） | B4: =SUM(H11:H210) -> 0 | D4: NISA口座 | E4: =SUMIF(D11:D210,"*NISA*",H11:H210) -> 0 | G4: 国内株式 | H4: =SUMIF(A11:A210,"国内株式*",H11:H210) -> 0
A5: 評価損益 合計（円） | B5: =SUM(I11:I210) -> 0 | D5: 特定口座 | E5: =SUMIF(D11:D210,"特定*",H11:H210) -> 0 | G5: 米国株式 | H5: =SUMIF(A11:A210,"米国株式*",H11:H210) -> 0
A6: 取得額 合計（円） | B6: =B4-B5 -> 0 | D6: 一般口座 | E6: =SUMIF(D11:D210,"一般*",H11:H210) -> 0 | G6: 投資信託 | H6: =SUMIF(A11:A210,"投資信託*",H11:H210) -> 0
A7: 評価損益率 | B7: =IF(B6=0,0,B5/B6) -> 0 | D7: （構成比 NISA） | E7: =IF($B$4=0,0,E4/$B$4) -> 0 | G7: その他 | H7: =B4-SUM(H4:H6) -> 0
A9: 投資信託 | B9: （例） | C9: eMAXIS Slim 全世界株式(オール・カントリー) | D9: NISAつみたて投資枠 | E9: 120000 | F9: 21500 | G9: 26800 | H9: 321600 | I9: 63600 | J9: =IF(OR(H9="",H9-I9=0),"",I9/(H9-I9)) -> 0.24651163 | K9: ← 記入例（集計に含まれません）
A10: 種別 | B10: 銘柄コード・ ティッカー | C10: 銘柄名 | D10: 口座 | E10: 保有数量 | F10: 平均取得価額 | G10: 現在値 | H10: 時価評価額 （円） | I10: 評価損益 （円） | J10: 評価損益率
J11: =IF(OR(H11="",H11-I11=0),"",I11/(H11-I11))
J12: =IF(OR(H12="",H12-I12=0),"",I12/(H12-I12))
J13: =IF(OR(H13="",H13-I13=0),"",I13/(H13-I13))
J14: =IF(OR(H14="",H14-I14=0),"",I14/(H14-I14))
J15: =IF(OR(H15="",H15-I15=0),"",I15/(H15-I15))
J16: =IF(OR(H16="",H16-I16=0),"",I16/(H16-I16))
J17: =IF(OR(H17="",H17-I17=0),"",I17/(H17-I17))
J18: =IF(OR(H18="",H18-I18=0),"",I18/(H18-I18))
J19: =IF(OR(H19="",H19-I19=0),"",I19/(H19-I19))
J20: =IF(OR(H20="",H20-I20=0),"",I20/(H20-I20))
J21: =IF(OR(H21="",H21-I21=0),"",I21/(H21-I21))
J22: =IF(OR(H22="",H22-I22=0),"",I22/(H22-I22))
... J210: =IF(OR(H210="",H210-I210=0),"",I210/(H210-I210))

Sheet 年次推移
A1: 年次推移（運用期間を過ぎた年は空欄）
A2: 金額の単位：円 ／ 積立は毎月末、月複利で計算
A4: 年目 | B4: 年齢 | C4: 毎月の積立額 | D4: 年間積立額 | E4: 元本累計 | F4: 年末の資産残高 | G4: 運用益累計 | H4: 税引後の資産 | I4: 今の価値に換算
A5: 0 | B5: =IF($A5>シミュレーション!$B$10,"",シミュレーション!$B$4+$A5) -> 35 | C5: 0 | D5: 0 | E5: =シミュレーション!$B$7 -> 0 | F5: =シミュレーション!$B$7 -> 0 | G5: =IF($A5>シミュレーション!$B$10,"",F5-E5) -> 0 | H5: =IF($A5>シミュレーション!$B$10,"",F5-MAX(G5,0)*シミュレーション!$B$12) -> 0 | I5: =IF($A5>シミュレーション!$B$10,"",H5/(1+シミュレーション!$B$13)^$A5) -> 0
A6: 1 | B6: =IF($A6>シミュレーション!$B$10,"",シミュレーション!$B$4+$A6) -> 36 | C6: =IF($A6>シミュレーション!$B$10,"",シミュレーション!$B$8*(1+シミュレーション!$B$11)^($A6-1)) -> 30000 | D6: =IF($A6>シミュレーション!$B$10,"",C6*12) -> 360000 | E6: =IF($A6>シミュレーション!$B$10,"",E5+D6) -> 360000 | F6: =IF($A6>シミュレーション!$B$10,"",FV(シミュレーション!$B$14,12,-C6,-F5)) -> 368177.33 | G6: =IF($A6>シミュレーション!$B$10,"",F6-E6) -> 8177.3259 | H6: =IF($A6>シミュレーション!$B$10,"",F6-MAX(G6,0)*シミュレーション!$B$12) -> 368177.33 | I6: =IF($A6>シミュレーション!$B$10,"",H6/(1+シミュレーション!$B$13)^$A6) -> 360958.16
A7: 2 | B7: =IF($A7>シミュレーション!$B$10,"",シミュレーション!$B$4+$A7) -> 37 | C7: =IF($A7>シミュレーション!$B$10,"",シミュレーション!$B$8*(1+シミュレーション!$B$11)^($A7-1)) -> 30000 | D7: =IF($A7>シミュレーション!$B$10,"",C7*12) -> 360000 | E7: =IF($A7>シミュレーション!$B$10,"",E6+D7) -> 720000 | F7: =IF($A7>シミュレーション!$B$10,"",FV(シミュレーション!$B$14,12,-C7,-F6)) -> 754763.52 | G7: =IF($A7>シミュレーション!$B$10,"",F7-E7) -> 34763.518 | H7: =IF($A7>シミュレーション!$B$10,"",F7-MAX(G7,0)*シミュレーション!$B$12) -> 754763.52 | I7: =IF($A7>シミュレーション!$B$10,"",H7/(1+シミュレーション!$B$13)^$A7) -> 725455.13
A8: 3 | B8: =IF($A8>シミュレーション!$B$10,"",シミュレーション!$B$4+$A8) -> 38 | C8: =IF($A8>シミュレーション!$B$10,"",シミュレーション!$B$8*(1+シミュレーション!$B$11)^($A8-1)) -> 30000 | D8: =IF($A8>シミュレーション!$B$10,"",C8*12) -> 360000 | E8: =IF($A8>シミュレーション!$B$10,"",E7+D8) -> 1080000 | F8: =IF($A8>シミュレーション!$B$10,"",FV(シミュレーション!$B$14,12,-C8,-F7)) -> 1160679 | G8: =IF($A8>シミュレーション!$B$10,"",F8-E8) -> 80679.02 | H8: =IF($A8>シミュレーション!$B$10,"",F8-MAX(G8,0)*シミュレーション!$B$12) -> 1160679 | I8: =IF($A8>シミュレーション!$B$10,"",H8/(1+シミュレーション!$B$13)^$A8) -> 1093733.8
A9: 4 | B9: =IF($A9>シミュレーション!$B$10,"",シミュレーション!$B$4+$A9) -> 39 | C9: =IF($A9>シミュレーション!$B$10,"",シミュレーション!$B$8*(1+シミュレーション!$B$11)^($A9-1)) -> 30000 | D9: =IF($A9>シミュレーション!$B$10,"",C9*12) -> 360000 | E9: =IF($A9>シミュレーション!$B$10,"",E8+D9) -> 1440000 | F9: =IF($A9>シミュレーション!$B$10,"",FV(シミュレーション!$B$14,12,-C9,-F8)) -> 1586890.3 | G9: =IF($A9>シミュレーション!$B$10,"",F9-E9) -> 146890.3 | H9: =IF($A9>シミュレーション!$B$10,"",F9-MAX(G9,0)*シミュレーション!$B$12) -> 1586890.3 | I9: =IF($A9>シミュレーション!$B$10,"",H9/(1+シミュレーション!$B$13)^$A9) -> 1466041.3
A10: 5 | B10: =IF($A10>シミュレーション!$B$10,"",シミュレーション!$B$4+$A10) -> 40 | C10: =IF($A10>シミュレーション!$B$10,"",シミュレーション!$B$8*(1+シミュレーション!$B$11)^($A10-1)) -> 30000 | D10: =IF($A10>シミュレーション!$B$10,"",C10*12) -> 360000 | E10: =IF($A10>シミュレーション!$B$10,"",E9+D10) -> 1800000 | F10: =IF($A10>シミュレーション!$B$10,"",FV(シミュレーション!$B$14,12,-C10,-F9)) -> 2034412.1 | G10: =IF($A10>シミュレーション!$B$10,"",F10-E10) -> 234412.14 | H10: =IF($A10>シミュレーション!$B$10,"",F10-MAX(G10,0)*シミュレーション!$B$12) -> 2034412.1 | I10: =IF($A10>シミュレーション!$B$10,"",H10/(1+シミュレーション!$B$13)^$A10) -> 1842629.8
A11: 6 | B11: =IF($A11>シミュレーション!$B$10,"",シミュレーション!$B$4+$A11) -> 41 | C11: =IF($A11>シミュレーション!$B$10,"",シミュレーション!$B$8*(1+シミュレーション!$B$11)^($A11-1)) -> 30000 | D11: =IF($A11>シミュレーション!$B$10,"",C11*12) -> 360000 | E11: =IF($A11>シミュレーション!$B$10,"",E10+D11) -> 2160000 | F11: =IF($A11>シミュレーション!$B$10,"",FV(シミュレーション!$B$14,12,-C11,-F10)) -> 2504310.1 | G11: =IF($A11>シミュレーション!$B$10,"",F11-E11) -> 344310.07 | H11: =IF($A11>シミュレーション!$B$10,"",F11-MAX(G11,0)*シミュレーション!$B$12) -> 2504310.1 | I11: =IF($A11>シミュレーション!$B$10,"",H11/(1+シミュレーション!$B$13)^$A11) -> 2223755.7
A12: 7 | B12: =IF($A12>シミュレーション!$B$10,"",シミュレーション!$B$4+$A12) -> 42 | C12: =IF($A12>シミュレーション!$B$10,"",シミュレーション!$B$8*(1+シミュレーション!$B$11)^($A12-1)) -> 30000 | D12: =IF($A12>シミュレーション!$B$10,"",C12*12) -> 360000 | E12: =IF($A12>シミュレーション!$B$10,"",E11+D12) -> 2520000 | F12: =IF($A12>シミュレーション!$B$10,"",FV(シミュレーション!$B$14,12,-C12,-F11)) -> 2997702.9 | G12: =IF($A12>シミュレーション!$B$10,"",F12-E12) -> 477702.9 | H12: =IF($A12>シミュレーション!$B$10,"",F12-MAX(G12,0)*シミュレーション!$B$12) -> 2997702.9 | I12: =IF($A12>シミュレーション!$B$10,"",H12/(1+シミュレーション!$B$13)^$A12) -> 2609680.8
A13: 8 | B13: =IF($A13>シミュレーション!$B$10,"",シミュレーション!$B$4+$A13) -> 43 | C13: =IF($A13>シミュレーション!$B$10,"",シミュレーション!$B$8*(1+シミュレーション!$B$11)^($A13-1)) -> 30000 | D13: =IF($A13>シミュレーション!$B$10,"",C13*12) -> 360000 | E13: =IF($A13>シミュレーション!$B$10,"",E12+D13) -> 2880000 | F13: =IF($A13>シミュレーション!$B$10,"",FV(シミュレーション!$B$14,12,-C13,-F12)) -> 3515765.4 | G13: =IF($A13>シミュレーション!$B$10,"",F13-E13) -> 635765.37 | H13: =IF($A13>シミュレーション!$B$10,"",F13-MAX(G13,0)*シミュレーション!$B$12) -> 3515765.4 | I13: =IF($A13>シミュレーション!$B$10,"",H13/(1+シミュレーション!$B$13)^$A13) -> 3000671.9
A14: 9 | B14: =IF($A14>シミュレーション!$B$10,"",シミュレーション!$B$4+$A14) -> 44 | C14: =IF($A14>シミュレーション!$B$10,"",シミュレーション!$B$8*(1+シミュレーション!$B$11)^($A14-1)) -> 30000 | D14: =IF($A14>シミュレーション!$B$10,"",C14*12) -> 360000 | E14: =IF($A14>シミュレーション!$B$10,"",E13+D14) -> 3240000 | F14: =IF($A14>シミュレーション!$B$10,"",FV(シミュレーション!$B$14,12,-C14,-F13)) -> 4059731 | G14: =IF($A14>シミュレーション!$B$10,"",F14-E14) -> 819730.96 | H14: =IF($A14>シミュレーション!$B$10,"",F14-MAX(G14,0)*シミュレーション!$B$12) -> 4059731 | I14: =IF($A14>シミュレーション!$B$10,"",H14/(1+シミュレーション!$B$13)^$A14) -> 3397001.3
A15: 10 | B15: =IF($A15>シミュレーション!$B$10,"",シミュレーション!$B$4+$A15) -> 45 | C15: =IF($A15>シミュレーション!$B$10,"",シミュレーション!$B$8*(1+シミュレーション!$B$11)^($A15-1)) -> 30000 | D15: =IF($A15>シミュレーション!$B$10,"",C15*12) -> 360000 | E15: =IF($A15>シミュレーション!$B$10,"",E14+D15) -> 3600000 | F15: =IF($A15>シミュレーション!$B$10,"",FV(シミュレーション!$B$14,12,-C15,-F14)) -> 4630894.8 | G15: =IF($A15>シミュレーション!$B$10,"",F15-E15) -> 1030894.8 | H15: =IF($A15>シミュレーション!$B$10,"",F15-MAX(G15,0)*シミュレーション!$B$12) -> 4630894.8 | I15: =IF($A15>シミュレーション!$B$10,"",H15/(1+シミュレーション!$B$13)^$A15) -> 3798946.7
A16: 11 | B16: =IF($A16>シミュレーション!$B$10,"",シミュレーション!$B$4+$A16) -> 46 | C16: =IF($A16>シミュレーション!$B$10,"",シミュレーション!$B$8*(1+シミュレーション!$B$11)^($A16-1)) -> 30000 | D16: =IF($A16>シミュレーション!$B$10,"",C16*12) -> 360000 | E16: =IF($A16>シミュレーション!$B$10,"",E15+D16) -> 3960000 | F16: =IF($A16>シミュレーション!$B$10,"",FV(シミュレーション!$B$14,12,-C16,-F15)) -> 5230616.9 | G16: =IF($A16>シミュレーション!$B$10,"",F16-E16) -> 1270616.9 | H16: =IF($A16>シミュレーション!$B$10,"",F16-MAX(G16,0)*シミュレーション!$B$12) -> 5230616.9 | I16: =IF($A16>シミュレーション!$B$10,"",H16/(1+シミュレーション!$B$13)^$A16) -> 4206791.8
A17: 12 | B17: =IF($A17>シミュレーション!$B$10,"",シミュレーション!$B$4+$A17) -> 47 | C17: =IF($A17>シミュレーション!$B$10,"",シミュレーション!$B$8*(1+シミュレーション!$B$11)^($A17-1)) -> 30000 | D17: =IF($A17>シミュレーション!$B$10,"",C17*12) -> 360000 | E17: =IF($A17>シミュレーション!$B$10,"",E16+D17) -> 4320000 | F17: =IF($A17>シミュレーション!$B$10,"",FV(シミュレーション!$B$14,12,-C17,-F16)) -> 5860325.1 | G17: =IF($A17>シミュレーション!$B$10,"",F17-E17) -> 1540325.1 | H17: =IF($A17>シミュレーション!$B$10,"",F17-MAX(G17,0)*シミュレーション!$B$12) -> 5860325.1 | I17: =IF($A17>シミュレーション!$B$10,"",H17/(1+シミュレーション!$B$13)^$A17) -> 4620826.3
... A55: 50 | B55: =IF($A55>シミュレーション!$B$10,"",シミュレーション!$B$4+$A55) | C55: =IF($A55>シミュレーション!$B$10,"",シミュレーション!$B$8*(1+シミュレーション!$B$11)^($A55-1)) | D55: =IF($A55>シミュレーション!$B$10,"",C55*12) | E55: =IF($A55>シミュレーション!$B$10,"",E54+D55) | F55: =IF($A55>シミュレーション!$B$10,"",FV(シミュレーション!$B$14,12,-C55,-F54)) | G55: =IF($A55>シミュレーション!$B$10,"",F55-E55) | H55: =IF($A55>シミュレーション!$B$10,"",F55-MAX(G55,0)*シミュレーション!$B$12) | I55: =IF($A55>シミュレーション!$B$10,"",H55/(1+シミュレーション!$B$13)^$A55)

Sheet 利回り比較
A1: 利回り×運用期間 別の最終資産額（円）
A2: 初期資産・毎月の積立額は「シミュレーション」シートの値を使用。積立額の増加率と税金は反映していません。
A5: 年利回り ＼ 期間 | B5: 5 | C5: 10 | D5: 15 | E5: 20 | F5: 25 | G5: 30 | H5: 35 | I5: 40
A6: 0 | B6: =FV((1+$A6)^(1/12)-1,B$5*12,-シミュレーション!$B$8,-シミュレーション!$B$7) -> 1800000 | C6: =FV((1+$A6)^(1/12)-1,C$5*12,-シミュレーション!$B$8,-シミュレーション!$B$7) -> 3600000 | D6: =FV((1+$A6)^(1/12)-1,D$5*12,-シミュレーション!$B$8,-シミュレーション!$B$7) -> 5400000 | E6: =FV((1+$A6)^(1/12)-1,E$5*12,-シミュレーション!$B$8,-シミュレーション!$B$7) -> 7200000 | F6: =FV((1+$A6)^(1/12)-1,F$5*12,-シミュレーション!$B$8,-シミュレーション!$B$7) -> 9000000 | G6: =FV((1+$A6)^(1/12)-1,G$5*12,-シミュレーション!$B$8,-シミュレーション!$B$7) -> 10800000 | H6: =FV((1+$A6)^(1/12)-1,H$5*12,-シミュレーション!$B$8,-シミュレーション!$B$7) -> 12600000 | I6: =FV((1+$A6)^(1/12)-1,I$5*12,-シミュレーション!$B$8,-シミュレーション!$B$7) -> 14400000
A7: 0.01 | B7: =FV((1+$A7)^(1/12)-1,B$5*12,-シミュレーション!$B$8,-シミュレーション!$B$7) -> 1844763.3 | C7: =FV((1+$A7)^(1/12)-1,C$5*12,-シミュレーション!$B$8,-シミュレーション!$B$7) -> 3783628.2 | D7: =FV((1+$A7)^(1/12)-1,D$5*12,-シミュレーション!$B$8,-シミュレーション!$B$7) -> 5821394.6 | E7: =FV((1+$A7)^(1/12)-1,E$5*12,-シミュレーション!$B$8,-シミュレーション!$B$7) -> 7963107.5 | F7: =FV((1+$A7)^(1/12)-1,F$5*12,-シミュレーション!$B$8,-シミュレーション!$B$7) -> 10214069 | G7: =FV((1+$A7)^(1/12)-1,G$5*12,-シミュレーション!$B$8,-シミュレーション!$B$7) -> 12579853 | H7: =FV((1+$A7)^(1/12)-1,H$5*12,-シミュレーション!$B$8,-シミュレーション!$B$7) -> 15066315 | I7: =FV((1+$A7)^(1/12)-1,I$5*12,-シミュレーション!$B$8,-シミュレーション!$B$7) -> 17679612
A8: 0.02 | B8: =FV((1+$A8)^(1/12)-1,B$5*12,-シミュレーション!$B$8,-シミュレーション!$B$7) -> 1890566.4 | C8: =FV((1+$A8)^(1/12)-1,C$5*12,-シミュレーション!$B$8,-シミュレーション!$B$7) -> 3977904.4 | D8: =FV((1+$A8)^(1/12)-1,D$5*12,-シミュレーション!$B$8,-シミュレーション!$B$7) -> 6282494.3 | E8: =FV((1+$A8)^(1/12)-1,E$5*12,-シミュレーション!$B$8,-シミュレーション!$B$7) -> 8826947.8 | F8: =FV((1+$A8)^(1/12)-1,F$5*12,-シミュレーション!$B$8,-シミュレーション!$B$7) -> 11636230 | G8: =FV((1+$A8)^(1/12)-1,G$5*12,-シミュレーション!$B$8,-シミュレーション!$B$7) -> 14737905 | H8: =FV((1+$A8)^(1/12)-1,H$5*12,-シミュレーション!$B$8,-シミュレーション!$B$7) -> 18162404 | I8: =FV((1+$A8)^(1/12)-1,I$5*12,-シミュレーション!$B$8,-シミュレーション!$B$7) -> 21943328
A9: 0.03 | B9: =FV((1+$A9)^(1/12)-1,B$5*12,-シミュレーション!$B$8,-シミュレーション!$B$7) -> 1937428.9 | C9: =FV((1+$A9)^(1/12)-1,C$5*12,-シミュレーション!$B$8,-シミュレーション!$B$7) -> 4183439.9 | D9: =FV((1+$A9)^(1/12)-1,D$5*12,-シミュレーション!$B$8,-シミュレーション!$B$7) -> 6787182.3 | E9: =FV((1+$A9)^(1/12)-1,E$5*12,-シミュレーション!$B$8,-シミュレーション!$B$7) -> 9805633.3 | F9: =FV((1+$A9)^(1/12)-1,F$5*12,-シミュレーション!$B$8,-シミュレーション!$B$7) -> 13304845 | G9: =FV((1+$A9)^(1/12)-1,G$5*12,-シミュレーション!$B$8,-シミュレーション!$B$7) -> 17361391 | H9: =FV((1+$A9)^(1/12)-1,H$5*12,-シミュレーション!$B$8,-シミュレーション!$B$7) -> 22064039 | I9: =FV((1+$A9)^(1/12)-1,I$5*12,-シミュレーション!$B$8,-シミュレーション!$B$7) -> 27515698
A10: 0.04 | B10: =FV((1+$A10)^(1/12)-1,B$5*12,-シミュレーション!$B$8,-シミュレーション!$B$7) -> 1985370.7 | C10: =FV((1+$A10)^(1/12)-1,C$5*12,-シミュレーション!$B$8,-シミュレーション!$B$7) -> 4400877.7 | D10: =FV((1+$A10)^(1/12)-1,D$5*12,-シミュレーション!$B$8,-シミュレーション!$B$7) -> 7339711.4 | E10: =FV((1+$A10)^(1/12)-1,E$5*12,-シミュレーション!$B$8,-シミュレーション!$B$7) -> 10915252 | F10: =FV((1+$A10)^(1/12)-1,F$5*12,-シミュレーション!$B$8,-シミュレーション!$B$7) -> 15265444 | G10: =FV((1+$A10)^(1/12)-1,G$5*12,-シミュレーション!$B$8,-シミュレーション!$B$7) -> 20558117 | H10: =FV((1+$A10)^(1/12)-1,H$5*12,-シミュレーション!$B$8,-シミュレーション!$B$7) -> 26997463 | I10: =FV((1+$A10)^(1/12)-1,I$5*12,-シミュレーション!$B$8,-シミュレーション!$B$7) -> 34831913
A11: 0.05 | B11: =FV((1+$A11)^(1/12)-1,B$5*12,-シミュレーション!$B$8,-シミュレーション!$B$7) -> 2034412.1 | C11: =FV((1+$A11)^(1/12)-1,C$5*12,-シミュレーション!$B$8,-シミュレーション!$B$7) -> 4630894.8 | D11: =FV((1+$A11)^(1/12)-1,D$5*12,-シミュレーション!$B$8,-シミュレーション!$B$7) -> 7944737.8 | E11: =FV((1+$A11)^(1/12)-1,E$5*12,-シミュレーション!$B$8,-シミュレーション!$B$7) -> 12174135 | F11: =FV((1+$A11)^(1/12)-1,F$5*12,-シミュレーション!$B$8,-シミュレーション!$B$7) -> 17572036 | G11: =FV((1+$A11)^(1/12)-1,G$5*12,-シミュレーション!$B$8,-シミュレーション!$B$7) -> 24461277 | H11: =FV((1+$A11)^(1/12)-1,H$5*12,-シミュレーション!$B$8,-シミュレーション!$B$7) -> 33253889 | I11: =FV((1+$A11)^(1/12)-1,I$5*12,-シミュレーション!$B$8,-シミュレーション!$B$7) -> 44475738
A12: 0.06 | B12: =FV((1+$A12)^(1/12)-1,B$5*12,-シミュレーション!$B$8,-シミュレーション!$B$7) -> 2084573.6 | C12: =FV((1+$A12)^(1/12)-1,C$5*12,-シミュレーション!$B$8,-シミュレーション!$B$7) -> 4874203.3 | D12: =FV((1+$A12)^(1/12)-1,D$5*12,-シミュレーション!$B$8,-シミュレーション!$B$7) -> 8607357.1 | E12: =FV((1+$A12)^(1/12)-1,E$5*12,-シミュレーション!$B$8,-シミュレーション!$B$7) -> 13603159 | F12: =FV((1+$A12)^(1/12)-1,F$5*12,-シミュレーション!$B$8,-シミュレーション!$B$7) -> 20288669 | G12: =FV((1+$A12)^(1/12)-1,G$5*12,-シミュレーション!$B$8,-シミュレーション!$B$7) -> 29235389 | H12: =FV((1+$A12)^(1/12)-1,H$5*12,-シミュレーション!$B$8,-シミュレーション!$B$7) -> 41208119 | I12: =FV((1+$A12)^(1/12)-1,I$5*12,-シミュレーション!$B$8,-シミュレーション!$B$7) -> 57230333
A13: 0.07 | B13: =FV((1+$A13)^(1/12)-1,B$5*12,-シミュレーション!$B$8,-シミュレーション!$B$7) -> 2135875.7 | C13: =FV((1+$A13)^(1/12)-1,C$5*12,-シミュレーション!$B$8,-シミュレーション!$B$7) -> 5131551.9 | D13: =FV((1+$A13)^(1/12)-1,D$5*12,-シミュレーション!$B$8,-シミュレーション!$B$7) -> 9333142.8 | E13: =FV((1+$A13)^(1/12)-1,E$5*12,-シミュレーション!$B$8,-シミュレーション!$B$7) -> 15226091 | F13: =FV((1+$A13)^(1/12)-1,F$5*12,-シミュレーション!$B$8,-シミュレーション!$B$7) -> 23491256 | G13: =FV((1+$A13)^(1/12)-1,G$5*12,-シミュレーション!$B$8,-シミュレーション!$B$7) -> 35083578 | H13: =FV((1+$A13)^(1/12)-1,H$5*12,-シミュレーション!$B$8,-シミュレーション!$B$7) -> 51342409 | I13: =FV((1+$A13)^(1/12)-1,I$5*12,-シミュレーション!$B$8,-シミュレーション!$B$7) -> 74146260
A14: 0.08 | B14: =FV((1+$A14)^(1/12)-1,B$5*12,-シミュレーション!$B$8,-シミュレーション!$B$7) -> 2188339.5 | C14: =FV((1+$A14)^(1/12)-1,C$5*12,-シミュレーション!$B$8,-シミュレーション!$B$7) -> 5403728.2 | D14: =FV((1+$A14)^(1/12)-1,D$5*12,-シミュレーション!$B$8,-シミュレーション!$B$7) -> 10128189 | E14: =FV((1+$A14)^(1/12)-1,E$5*12,-シミュレーション!$B$8,-シミュレーション!$B$7) -> 17069972 | F14: =FV((1+$A14)^(1/12)-1,F$5*12,-シミュレーション!$B$8,-シミュレーション!$B$7) -> 27269729 | G14: =FV((1+$A14)^(1/12)-1,G$5*12,-シミュレーション!$B$8,-シミュレーション!$B$7) -> 42256518 | H14: =FV((1+$A14)^(1/12)-1,H$5*12,-シミュレーション!$B$8,-シミュレーション!$B$7) -> 64277027 | I14: =FV((1+$A14)^(1/12)-1,I$5*12,-シミュレーション!$B$8,-シミュレーション!$B$7) -> 96632380
A15: 0.09 | B15: =FV((1+$A15)^(1/12)-1,B$5*12,-シミュレーション!$B$8,-シミュレーション!$B$7) -> 2241986.1 | C15: =FV((1+$A15)^(1/12)-1,C$5*12,-シミュレーション!$B$8,-シミュレーション!$B$7) -> 5691559.6 | D15: =FV((1+$A15)^(1/12)-1,D$5*12,-シミュレーション!$B$8,-シミュレーション!$B$7) -> 10999156 | E15: =FV((1+$A15)^(1/12)-1,E$5*12,-シミュレーション!$B$8,-シミュレーション!$B$7) -> 19165551 | F15: =FV((1+$A15)^(1/12)-1,F$5*12,-シミュレーション!$B$8,-シミュレーション!$B$7) -> 31730562 | G15: =FV((1+$A15)^(1/12)-1,G$5*12,-シミュレーション!$B$8,-シミュレーション!$B$7) -> 51063389 | H15: =FV((1+$A15)^(1/12)-1,H$5*12,-シミュレーション!$B$8,-シミュレーション!$B$7) -> 80809340 | I15: =FV((1+$A15)^(1/12)-1,I$5*12,-シミュレーション!$B$8,-シミュレーション!$B$7) -> 1.2657717e+08
A16: 0.1 | B16: =FV((1+$A16)^(1/12)-1,B$5*12,-シミュレーション!$B$8,-シミュレーション!$B$7) -> 2296836.9 | C16: =FV((1+$A16)^(1/12)-1,C$5*12,-シミュレーション!$B$8,-シミュレーション!$B$7) -> 5995915.7 | D16: =FV((1+$A16)^(1/12)-1,D$5*12,-シミュレーション!$B$8,-シミュレーション!$B$7) -> 11953319 | E16: =FV((1+$A16)^(1/12)-1,E$5*12,-シミュレーション!$B$8,-シミュレーション!$B$7) -> 21547777 | F16: =FV((1+$A16)^(1/12)-1,F$5*12,-シミュレーション!$B$8,-シミュレーション!$B$7) -> 36999747 | G16: =FV((1+$A16)^(1/12)-1,G$5*12,-シミュレーション!$B$8,-シミュレーション!$B$7) -> 61885299 | H16: =FV((1+$A16)^(1/12)-1,H$5*12,-シミュレーション!$B$8,-シミュレーション!$B$7) -> 1.0196373e+08 | I16: =FV((1+$A16)^(1/12)-1,I$5*12,-シミュレーション!$B$8,-シミュレーション!$B$7) -> 1.6651044e+08
A17: （参考）元本合計 | B17: =シミュレーション!$B$7+シミュレーション!$B$8*12*B$5 -> 1800000 | C17: =シミュレーション!$B$7+シミュレーション!$B$8*12*C$5 -> 3600000 | D17: =シミュレーション!$B$7+シミュレーション!$B$8*12*D$5 -> 5400000 | E17: =シミュレーション!$B$7+シミュレーション!$B$8*12*E$5 -> 7200000 | F17: =シミュレーション!$B$7+シミュレーション!$B$8*12*F$5 -> 9000000 | G17: =シミュレーション!$B$7+シミュレーション!$B$8*12*G$5 -> 10800000 | H17: =シミュレーション!$B$7+シミュレーション!$B$8*12*H$5 -> 12600000 | I17: =シミュレーション!$B$7+シミュレーション!$B$8*12*I$5 -> 14400000
